{
  "sections": {
    "a4b5e10c-91be-487d-b223-abdded7b196e": {
      "type": "image-banner",
      "blocks": {
        "template--14546355290246__a4b5e10c-91be-487d-b223-abdded7b196e-1674759332d4096a7f-0": {
          "type": "heading",
          "disabled": true,
          "settings": {
            "heading": "Image banner",
            "heading_size": "h1"
          }
        },
        "template--14546355290246__a4b5e10c-91be-487d-b223-abdded7b196e-1674759332d4096a7f-1": {
          "type": "text",
          "disabled": true,
          "settings": {
            "text": "Give customers details about the banner image(s) or content on the template.",
            "text_style": "body"
          }
        },
        "template--14546355290246__a4b5e10c-91be-487d-b223-abdded7b196e-1674759332d4096a7f-2": {
          "type": "buttons",
          "disabled": true,
          "settings": {
            "button_label_1": "Button label",
            "button_link_1": "",
            "button_style_secondary_1": true,
            "button_label_2": "Button label",
            "button_link_2": "",
            "button_style_secondary_2": false
          }
        }
      },
      "block_order": [
        "template--14546355290246__a4b5e10c-91be-487d-b223-abdded7b196e-1674759332d4096a7f-0",
        "template--14546355290246__a4b5e10c-91be-487d-b223-abdded7b196e-1674759332d4096a7f-1",
        "template--14546355290246__a4b5e10c-91be-487d-b223-abdded7b196e-1674759332d4096a7f-2"
      ],
      "settings": {
        "image": "shopify:\/\/shop_images\/Screenshot_2023-01-23_at_13.02.28.png",
        "image_2": "shopify:\/\/shop_images\/Slide_Velodrom_by_Laser_-_3.jpg",
        "image_overlay_opacity": 30,
        "image_height": "large",
        "adapt_height_first_image": false,
        "desktop_content_position": "middle-center",
        "show_text_box": true,
        "desktop_content_alignment": "center",
        "color_scheme": "background-1",
        "mobile_content_alignment": "center",
        "stack_images_on_mobile": true,
        "show_text_below": true
      }
    },
    "e0911e38-e306-463a-9877-cdf1960a5028": {
      "type": "slideshow",
      "blocks": {
        "6242f8ed-ab30-4dd2-b15b-eb2f09cee6bf": {
          "type": "slide",
          "settings": {
            "image": "shopify:\/\/shop_images\/Screenshot_2023-01-23_at_13.02.28.png",
            "heading": "Early'23 collection",
            "heading_size": "h1",
            "subheading": "VELODROM",
            "button_label": "Shop Now",
            "link": "shopify:\/\/collections\/velodrom-strtwr-early23-collection",
            "button_style_secondary": false,
            "box_align": "middle-center",
            "show_text_box": false,
            "text_alignment": "center",
            "image_overlay_opacity": 0,
            "color_scheme": "background-1",
            "text_alignment_mobile": "center"
          }
        },
        "template--14546355290246__e0911e38-e306-463a-9877-cdf1960a5028-16686086846f083c6b-0": {
          "type": "slide",
          "settings": {
            "image": "shopify:\/\/shop_images\/Wide_2022.09-hd.jpg",
            "heading": "Autum\/Winter 2022",
            "heading_size": "h1",
            "subheading": "PAS NORMAL STUDIO",
            "button_label": "Shop Collection",
            "link": "shopify:\/\/collections\/pas-normal-studios-autumn-winter-22",
            "button_style_secondary": false,
            "box_align": "middle-left",
            "show_text_box": false,
            "text_alignment": "center",
            "image_overlay_opacity": 10,
            "color_scheme": "background-1",
            "text_alignment_mobile": "center"
          }
        },
        "template--14546355290246__e0911e38-e306-463a-9877-cdf1960a5028-16686086846f083c6b-1": {
          "type": "slide",
          "settings": {
            "image": "shopify:\/\/shop_images\/grid2.jpg",
            "heading": "The new and amazing bike from ENVE",
            "heading_size": "h1",
            "subheading": "ENVE MELEE BIKE",
            "button_label": "Button label",
            "link": "shopify:\/\/products\/enve-melee-bike-frameset",
            "button_style_secondary": false,
            "box_align": "middle-left",
            "show_text_box": false,
            "text_alignment": "center",
            "image_overlay_opacity": 0,
            "color_scheme": "background-1",
            "text_alignment_mobile": "center"
          }
        }
      },
      "block_order": [
        "6242f8ed-ab30-4dd2-b15b-eb2f09cee6bf",
        "template--14546355290246__e0911e38-e306-463a-9877-cdf1960a5028-16686086846f083c6b-0",
        "template--14546355290246__e0911e38-e306-463a-9877-cdf1960a5028-16686086846f083c6b-1"
      ],
      "settings": {
        "layout": "full_bleed",
        "slide_height": "small",
        "slider_visual": "dots",
        "auto_rotate": true,
        "change_slides_speed": 9,
        "show_text_below": false,
        "accessibility_info": "Slideshow about our brand"
      }
    },
    "81eb5dff-ea73-49d9-945f-59d6b676ce36": {
      "type": "featured-collection",
      "settings": {
        "title": "NEW ARRIVALS",
        "heading_size": "h2",
        "description": "<p>Discover the latest additions to our range of clothing<\/p>",
        "show_description": false,
        "description_style": "body",
        "collection": "new-arrivals",
        "products_to_show": 12,
        "columns_desktop": 5,
        "full_width": false,
        "show_view_all": true,
        "view_all_style": "solid",
        "enable_desktop_slider": true,
        "color_scheme": "background-1",
        "image_ratio": "square",
        "show_secondary_image": false,
        "show_vendor": false,
        "show_rating": false,
        "enable_quick_add": false,
        "columns_mobile": "2",
        "swipe_on_mobile": true,
        "padding_top": 36,
        "padding_bottom": 36
      }
    },
    "5c87412e-d4b0-440b-94e5-b4c77e0eec42": {
      "type": "multicolumn",
      "blocks": {
        "template--14546355290246__5c87412e-d4b0-440b-94e5-b4c77e0eec42-1674732779c0a0a58f-0": {
          "type": "column",
          "settings": {
            "image": "shopify:\/\/shop_images\/local_shipping_FILL0_wght400_GRAD0_opsz48.png",
            "title": "FAST NATIONAL SHIPPING SPAIN",
            "text": "<p>Lorem ipsum<\/p>",
            "link_label": "",
            "link": ""
          }
        },
        "template--14546355290246__5c87412e-d4b0-440b-94e5-b4c77e0eec42-1674732779c0a0a58f-1": {
          "type": "column",
          "settings": {
            "image": "shopify:\/\/shop_images\/directions_boat_FILL0_wght400_GRAD0_opsz48.png",
            "title": "",
            "text": "<p><strong>FAST INTERNATIONAL SHIPPING<\/strong><\/p>",
            "link_label": "",
            "link": ""
          }
        },
        "template--14546355290246__5c87412e-d4b0-440b-94e5-b4c77e0eec42-1674732779c0a0a58f-2": {
          "type": "column",
          "settings": {
            "image": "shopify:\/\/shop_images\/cached_FILL0_wght400_GRAD0_opsz48.png",
            "title": "",
            "text": "<p><strong>FREE SIZE EXCHANGE IN EUROPE<\/strong><\/p>",
            "link_label": "",
            "link": ""
          }
        }
      },
      "block_order": [
        "template--14546355290246__5c87412e-d4b0-440b-94e5-b4c77e0eec42-1674732779c0a0a58f-0",
        "template--14546355290246__5c87412e-d4b0-440b-94e5-b4c77e0eec42-1674732779c0a0a58f-1",
        "template--14546355290246__5c87412e-d4b0-440b-94e5-b4c77e0eec42-1674732779c0a0a58f-2"
      ],
      "settings": {
        "title": "",
        "heading_size": "h2",
        "image_width": "third",
        "image_ratio": "adapt",
        "columns_desktop": 3,
        "column_alignment": "center",
        "background_style": "primary",
        "button_label": "",
        "button_link": "",
        "color_scheme": "background-1",
        "columns_mobile": "1",
        "swipe_on_mobile": false,
        "padding_top": 36,
        "padding_bottom": 36
      }
    },
    "collage": {
      "type": "collage",
      "blocks": {
        "dd696413-cfea-4a69-abb3-3a225aa4ba27": {
          "type": "image",
          "settings": {
            "image": "shopify:\/\/shop_images\/home_page_600x_crop_center_0dbf4dae-1a3a-4b55-9219-5c717eb79c58.webp",
            "image_link": "shopify:\/\/pages\/newsletter-signup",
            "image_padding": false
          }
        },
        "7a5f5fbc-e2be-4635-938a-61ad39a4523f": {
          "type": "product",
          "settings": {
            "product": "velodrom-vcc-javingfun-casual-tshirt-cream",
            "second_image": false
          }
        },
        "e007b13e-0038-44d5-95dc-4600e34655b1": {
          "type": "product",
          "settings": {
            "product": "pas-normal-studios-escapism-down-vest-army-green",
            "second_image": false
          }
        },
        "dd5cc332-7111-4399-8ed0-8e0e163a23ea": {
          "type": "product",
          "settings": {
            "product": "brandblack-rare-metal-ii-casual-shoes-orange-grey-orgy",
            "second_image": false
          }
        },
        "39949fdc-0f9c-46bc-868d-5f727b155b5a": {
          "type": "product",
          "settings": {
            "product": "laser-doctor-dou-5-panel-hat-corduroy-multi-color",
            "second_image": false
          }
        }
      },
      "block_order": [
        "dd696413-cfea-4a69-abb3-3a225aa4ba27",
        "7a5f5fbc-e2be-4635-938a-61ad39a4523f",
        "e007b13e-0038-44d5-95dc-4600e34655b1",
        "dd5cc332-7111-4399-8ed0-8e0e163a23ea",
        "39949fdc-0f9c-46bc-868d-5f727b155b5a"
      ],
      "settings": {
        "heading": "",
        "heading_size": "h2",
        "desktop_layout": "left",
        "mobile_layout": "collage",
        "card_styles": "product-card-wrapper",
        "color_scheme": "background-1",
        "padding_top": 36,
        "padding_bottom": 36
      }
    },
    "e4ad0f87-69fc-4ab1-a711-1a7b96eabf86": {
      "type": "collage",
      "blocks": {
        "d5114076-50ea-4407-b011-53683a1d9e29": {
          "type": "image",
          "settings": {
            "image": "shopify:\/\/shop_images\/homepageyeti.webp",
            "image_link": "shopify:\/\/collections\/yeti",
            "image_padding": false
          }
        },
        "ae364c5b-0dfe-4c90-960c-d1e02eda3663": {
          "type": "collection",
          "settings": {
            "collection": "laser-barcelona"
          }
        },
        "template--14546355290246__e4ad0f87-69fc-4ab1-a711-1a7b96eabf86-16686085946a160927-2": {
          "type": "collection",
          "settings": {
            "collection": "velodrom-pockets-collection"
          }
        },
        "60ca8f96-d519-40d3-b398-9c36b6b563ea": {
          "type": "image",
          "settings": {
            "image": "shopify:\/\/shop_images\/filantev2_600x_crop_center_f12bcae7-56ad-4726-8247-ffa56f60dde6.jpg",
            "image_link": "https:\/\/velodrom.dreambikebuilder.com\/",
            "image_padding": false
          }
        },
        "0e727a75-b267-40ec-9570-d94f0502dea7": {
          "type": "collection",
          "settings": {
            "collection": "eyewear"
          }
        }
      },
      "block_order": [
        "d5114076-50ea-4407-b011-53683a1d9e29",
        "ae364c5b-0dfe-4c90-960c-d1e02eda3663",
        "template--14546355290246__e4ad0f87-69fc-4ab1-a711-1a7b96eabf86-16686085946a160927-2",
        "60ca8f96-d519-40d3-b398-9c36b6b563ea",
        "0e727a75-b267-40ec-9570-d94f0502dea7"
      ],
      "settings": {
        "heading": "",
        "heading_size": "h1",
        "desktop_layout": "right",
        "mobile_layout": "collage",
        "card_styles": "product-card-wrapper",
        "color_scheme": "background-1",
        "padding_top": 36,
        "padding_bottom": 36
      }
    },
    "multicolumn": {
      "type": "multicolumn",
      "disabled": true,
      "blocks": {
        "column1": {
          "type": "column",
          "settings": {
            "title": "",
            "text": "<p>🚚 FAST NATIONAL SHIPPING SPAIN<\/p>",
            "link_label": "",
            "link": ""
          }
        },
        "column2": {
          "type": "column",
          "settings": {
            "title": "",
            "text": "<p>🎁 FAST INTERNATIONAL SHIPPING<\/p>",
            "link_label": "",
            "link": ""
          }
        },
        "column3": {
          "type": "column",
          "settings": {
            "title": "",
            "text": "<p>🔄 FREE SIZE EXCHANGE IN EUROPE<\/p>",
            "link_label": "",
            "link": ""
          }
        }
      },
      "block_order": [
        "column1",
        "column2",
        "column3"
      ],
      "settings": {
        "title": "",
        "heading_size": "h1",
        "image_width": "third",
        "image_ratio": "adapt",
        "columns_desktop": 3,
        "column_alignment": "center",
        "background_style": "none",
        "button_label": "",
        "button_link": "",
        "color_scheme": "background-1",
        "columns_mobile": "1",
        "swipe_on_mobile": true,
        "padding_top": 36,
        "padding_bottom": 36
      }
    },
    "3f450f81-8ef5-4cb4-9131-0db3d899a279": {
      "type": "collection-list",
      "blocks": {
        "template--14546355290246__3f450f81-8ef5-4cb4-9131-0db3d899a279-1668608594fd6afd40-0": {
          "type": "featured_collection",
          "settings": {
            "collection": "maap"
          }
        },
        "template--14546355290246__3f450f81-8ef5-4cb4-9131-0db3d899a279-1668608594fd6afd40-1": {
          "type": "featured_collection",
          "settings": {
            "collection": "cafe-du-cycliste"
          }
        },
        "7b87dc12-4e12-4daa-bf45-03a9f9645e67": {
          "type": "featured_collection",
          "settings": {
            "collection": "ndlss"
          }
        },
        "template--14546355290246__3f450f81-8ef5-4cb4-9131-0db3d899a279-1668608594fd6afd40-2": {
          "type": "featured_collection",
          "settings": {
            "collection": "tactic"
          }
        },
        "7f36f87d-a7d3-461e-9530-37a8061668f2": {
          "type": "featured_collection",
          "settings": {
            "collection": "fingerscrossed"
          }
        },
        "e909b6fe-416a-4f6e-bb26-045ea4944158": {
          "type": "featured_collection",
          "settings": {
            "collection": "erstwhile"
          }
        },
        "90033165-845c-4b78-af1b-0d41d8db1735": {
          "type": "featured_collection",
          "settings": {
            "collection": "pas-normal-studios"
          }
        }
      },
      "block_order": [
        "template--14546355290246__3f450f81-8ef5-4cb4-9131-0db3d899a279-1668608594fd6afd40-0",
        "template--14546355290246__3f450f81-8ef5-4cb4-9131-0db3d899a279-1668608594fd6afd40-1",
        "7b87dc12-4e12-4daa-bf45-03a9f9645e67",
        "template--14546355290246__3f450f81-8ef5-4cb4-9131-0db3d899a279-1668608594fd6afd40-2",
        "7f36f87d-a7d3-461e-9530-37a8061668f2",
        "e909b6fe-416a-4f6e-bb26-045ea4944158",
        "90033165-845c-4b78-af1b-0d41d8db1735"
      ],
      "settings": {
        "title": "APPAREL BRANDS",
        "heading_size": "h2",
        "image_ratio": "adapt",
        "columns_desktop": 5,
        "color_scheme": "background-1",
        "show_view_all": false,
        "columns_mobile": "1",
        "swipe_on_mobile": true,
        "padding_top": 36,
        "padding_bottom": 36
      }
    },
    "4c322433-45f4-4925-8736-535bb7314d61": {
      "type": "image-with-text",
      "blocks": {
        "template--14546355290246__4c322433-45f4-4925-8736-535bb7314d61-1668608684e46b6877-0": {
          "type": "heading",
          "settings": {
            "heading": "BRANDBLACK",
            "heading_size": "h1"
          }
        },
        "template--14546355290246__4c322433-45f4-4925-8736-535bb7314d61-1668608684e46b6877-1": {
          "type": "text",
          "settings": {
            "text": "<p>BE RARE. Brandblack is the ultimate shoe brand.<\/p>",
            "text_style": "body"
          }
        },
        "template--14546355290246__4c322433-45f4-4925-8736-535bb7314d61-1668608684e46b6877-2": {
          "type": "button",
          "settings": {
            "button_label": "Shop Now",
            "button_link": "shopify:\/\/collections\/brandblack"
          }
        }
      },
      "block_order": [
        "template--14546355290246__4c322433-45f4-4925-8736-535bb7314d61-1668608684e46b6877-0",
        "template--14546355290246__4c322433-45f4-4925-8736-535bb7314d61-1668608684e46b6877-1",
        "template--14546355290246__4c322433-45f4-4925-8736-535bb7314d61-1668608684e46b6877-2"
      ],
      "settings": {
        "image": "shopify:\/\/shop_images\/BRANDBLACK_SHOES.jpg",
        "height": "adapt",
        "desktop_image_width": "medium",
        "layout": "image_first",
        "desktop_content_position": "middle",
        "desktop_content_alignment": "left",
        "content_layout": "no-overlap",
        "color_scheme": "background-1",
        "mobile_content_alignment": "left",
        "padding_top": 36,
        "padding_bottom": 36
      }
    },
    "82567d4d-8ae0-45d7-a3be-82328b8203f7": {
      "type": "image-with-text",
      "blocks": {
        "template--14546355290246__82567d4d-8ae0-45d7-a3be-82328b8203f7-1668608684e46b6877-0": {
          "type": "heading",
          "settings": {
            "heading": "HAMMERHEAD KAROO",
            "heading_size": "h1"
          }
        },
        "template--14546355290246__82567d4d-8ae0-45d7-a3be-82328b8203f7-1668608684e46b6877-1": {
          "type": "text",
          "settings": {
            "text": "<p>Available now in Velodrom. Stay ahead of the competition with Hammerhead Karoo.<\/p>",
            "text_style": "body"
          }
        },
        "template--14546355290246__82567d4d-8ae0-45d7-a3be-82328b8203f7-1668608684e46b6877-2": {
          "type": "button",
          "settings": {
            "button_label": "Shop Now",
            "button_link": "shopify:\/\/products\/hammerhead-karoo-2-cycling-gps"
          }
        }
      },
      "block_order": [
        "template--14546355290246__82567d4d-8ae0-45d7-a3be-82328b8203f7-1668608684e46b6877-0",
        "template--14546355290246__82567d4d-8ae0-45d7-a3be-82328b8203f7-1668608684e46b6877-1",
        "template--14546355290246__82567d4d-8ae0-45d7-a3be-82328b8203f7-1668608684e46b6877-2"
      ],
      "settings": {
        "image": "shopify:\/\/shop_images\/hammerhead_karoo.jpg",
        "height": "adapt",
        "desktop_image_width": "medium",
        "layout": "text_first",
        "desktop_content_position": "middle",
        "desktop_content_alignment": "left",
        "content_layout": "no-overlap",
        "color_scheme": "background-1",
        "mobile_content_alignment": "left",
        "padding_top": 36,
        "padding_bottom": 36
      }
    },
    "85bca2a0-303e-464e-8f28-8945a53e06e4": {
      "type": "featured-collection",
      "settings": {
        "title": "VELODROM VCC",
        "heading_size": "h2",
        "description": "<p>DISCOVER THE VELODROM VCC WINTER COLLECTION<\/p>",
        "show_description": false,
        "description_style": "body",
        "collection": "velodrom-vcc",
        "products_to_show": 12,
        "columns_desktop": 5,
        "full_width": false,
        "show_view_all": true,
        "view_all_style": "solid",
        "enable_desktop_slider": true,
        "color_scheme": "background-1",
        "image_ratio": "square",
        "show_secondary_image": false,
        "show_vendor": false,
        "show_rating": false,
        "enable_quick_add": false,
        "columns_mobile": "2",
        "swipe_on_mobile": false,
        "padding_top": 36,
        "padding_bottom": 36
      }
    }
  },
  "order": [
    "a4b5e10c-91be-487d-b223-abdded7b196e",
    "e0911e38-e306-463a-9877-cdf1960a5028",
    "81eb5dff-ea73-49d9-945f-59d6b676ce36",
    "5c87412e-d4b0-440b-94e5-b4c77e0eec42",
    "collage",
    "e4ad0f87-69fc-4ab1-a711-1a7b96eabf86",
    "multicolumn",
    "3f450f81-8ef5-4cb4-9131-0db3d899a279",
    "4c322433-45f4-4925-8736-535bb7314d61",
    "82567d4d-8ae0-45d7-a3be-82328b8203f7",
    "85bca2a0-303e-464e-8f28-8945a53e06e4"
  ]
}
